azac/__init__.py
azac/azac_core.py
azac-0.1.1.dist-info/LICENSE.md
azac-0.1.1.dist-info/METADATA
azac-0.1.1.dist-info/WHEEL
azac-0.1.1.dist-info/top_level.txt
azac-0.1.1.dist-info/RECORD
