Metadata-Version: 2.1
Name: azac
Version: 0.1.1
Summary: From A to Z as Code
Author-email: Mikolaj Zabinski <mzabinski94@gmail.com>
Classifier: Development Status :: 1 - Planning
Classifier: Intended Audience :: Developers
Classifier: Programming Language :: Python :: 3
Classifier: Operating System :: Unix
Classifier: Operating System :: MacOS :: MacOS X
Classifier: Operating System :: Microsoft :: Windows
Requires-Python: >=3.8
License-File: LICENSE.md
